{"container_type": "Author", "filled": ["basics", "publications", "indices", "counts"], "scholar_id": "iuJ1buQAAAAJ", "source": "AUTHOR_PROFILE_PAGE", "name": "Zhengyi Zhao", "url_picture": "https://scholar.googleusercontent.com/citations?view_op=view_photo&user=iuJ1buQAAAAJ&citpid=1", "affiliation": "Southeast University, Alibaba Group", "interests": ["3D-reconstruction", "AIGC"], "email_domain": "@alibaba-inc.com", "citedby": 77, "publications": {"iuJ1buQAAAAJ:IjCSPb-OGe4C": {"container_type": "Publication", "source": "AUTHOR_PUBLICATION_ENTRY", "bib": {"title": "Hand-3d-studio: A new multi-view system for 3d hand reconstruction", "pub_year": "2020"}, "filled": false, "author_pub_id": "iuJ1buQAAAAJ:IjCSPb-OGe4C", "num_citations": 39, "citedby_url": "https://scholar.google.com/scholar?oi=bibs&hl=en&cites=14776650931359219849", "cites_id": ["14776650931359219849"]}, "iuJ1buQAAAAJ:Tyk-4Ss8FVUC": {"container_type": "Publication", "source": "AUTHOR_PUBLICATION_ENTRY", "bib": {"title": "Videomv: Consistent multi-view generation based on large video generative model", "pub_year": "2024"}, "filled": false, "author_pub_id": "iuJ1buQAAAAJ:Tyk-4Ss8FVUC", "num_citations": 22, "citedby_url": "https://scholar.google.com/scholar?oi=bibs&hl=en&cites=3910690493732643823", "cites_id": ["3910690493732643823"]}, "iuJ1buQAAAAJ:W7OEmFMy1HYC": {"container_type": "Publication", "source": "AUTHOR_PUBLICATION_ENTRY", "bib": {"title": "Gpld3d: Latent diffusion of 3d shape generative models by enforcing geometric and physical priors", "pub_year": "2024"}, "filled": false, "author_pub_id": "iuJ1buQAAAAJ:W7OEmFMy1HYC", "num_citations": 8, "citedby_url": "https://scholar.google.com/scholar?oi=bibs&hl=en&cites=15347435627009507148", "cites_id": ["15347435627009507148"]}, "iuJ1buQAAAAJ:YsMSGLbcyi4C": {"container_type": "Publication", "source": "AUTHOR_PUBLICATION_ENTRY", "bib": {"title": "High-Fidelity 3D Textured Shapes Generation by Sparse Encoding and Adversarial Decoding", "pub_year": "2024"}, "filled": false, "author_pub_id": "iuJ1buQAAAAJ:YsMSGLbcyi4C", "num_citations": 5, "citedby_url": "https://scholar.google.com/scholar?oi=bibs&hl=en&cites=964562148442436765", "cites_id": ["964562148442436765"]}, "iuJ1buQAAAAJ:WF5omc3nYNoC": {"container_type": "Publication", "source": "AUTHOR_PUBLICATION_ENTRY", "bib": {"title": "MCMat: Multiview-Consistent and Physically Accurate PBR Material Generation", "pub_year": "2024"}, "filled": false, "author_pub_id": "iuJ1buQAAAAJ:WF5omc3nYNoC", "num_citations": 2, "citedby_url": "https://scholar.google.com/scholar?oi=bibs&hl=en&cites=6772377158604947042", "cites_id": ["6772377158604947042"]}, "iuJ1buQAAAAJ:Y0pCki6q_DkC": {"container_type": "Publication", "source": "AUTHOR_PUBLICATION_ENTRY", "bib": {"title": "An Optimization Framework to Enforce Multi-View Consistency for Texturing 3D Meshes Using Pre-Trained Text-to-Image Models", "pub_year": "2024"}, "filled": false, "author_pub_id": "iuJ1buQAAAAJ:Y0pCki6q_DkC", "num_citations": 1, "citedby_url": "https://scholar.google.com/scholar?oi=bibs&hl=en&cites=5587456932224976465,632291360095478542", "cites_id": ["5587456932224976465", "632291360095478542"]}, "iuJ1buQAAAAJ:zYLM7Y9cAGgC": {"container_type": "Publication", "source": "AUTHOR_PUBLICATION_ENTRY", "bib": {"title": "PanoViT: Vision Transformer for Room Layout Estimation from a Single Panoramic Image", "pub_year": "2022"}, "filled": false, "author_pub_id": "iuJ1buQAAAAJ:zYLM7Y9cAGgC", "num_citations": 0}}, "citedby5y": 77, "hindex": 4, "hindex5y": 4, "i10index": 2, "i10index5y": 2, "cites_per_year": {"2020": 2, "2021": 6, "2022": 12, "2023": 13, "2024": 30, "2025": 14}, "updated": "2025-05-05 08:27:49.149268"}